weibo_mcp_server/__init__.py
weibo_mcp_server/server.py
weibo_mcp_server-0.1.0.dist-info/METADATA
weibo_mcp_server-0.1.0.dist-info/WHEEL
weibo_mcp_server-0.1.0.dist-info/entry_points.txt
weibo_mcp_server-0.1.0.dist-info/RECORD
