Metadata-Version: 2.4
Name: weibo-mcp-server
Version: 0.1.0
Summary: MCP weibo project
Author-email: "yooki.k" <yooki.k613@gmail.com>
Requires-Python: >=3.10
Requires-Dist: lxml>=5.3.2
Requires-Dist: mcp>=1.6.0
Requires-Dist: requests>=2.32.3
